mt/skimage/__init__.py
mt/skimage/poly_approx.py
mt/skimage/version.py
mtskimage-0.2.2.dist-info/LICENSE
mtskimage-0.2.2.dist-info/METADATA
mtskimage-0.2.2.dist-info/WHEEL
mtskimage-0.2.2.dist-info/top_level.txt
mtskimage-0.2.2.dist-info/RECORD
